server_packages/__init__.py
server_packages/common/__init__.py
server_packages/common/descriptors.py
server_packages/common/metaclasses.py
server_packages/common/utils.py
server_packages/common/variables.py
server_packages/doc/__init__.py
server_packages/doc/conf.py
server_packages/log/__init__.py
server_packages/log/config_log/__init__.py
server_packages/log/config_log/config_server_log.py
server_packages/log/config_log/decos.py
server_packages/server/__init__.py
server_packages/server/add_user.py
server_packages/server/config_window.py
server_packages/server/core.py
server_packages/server/main_window.py
server_packages/server/remove_user.py
server_packages/server/server_database.py
server_packages/server/start_server.py
server_packages/server/stat_window.py
server_packages/unit_tests/__init__.py
server_packages/unit_tests/test_server.py
server_packages/unit_tests/test_utils.py
Server_messenger-0.1.dist-info/METADATA
Server_messenger-0.1.dist-info/WHEEL
Server_messenger-0.1.dist-info/top_level.txt
Server_messenger-0.1.dist-info/RECORD
