Metadata-Version: 2.1
Name: Server-messenger
Version: 0.1
Summary: Server_messenger
Home-page: UNKNOWN
Author: Pavel Usov
Author-email: 
License: UNKNOWN
Platform: UNKNOWN
Requires-Dist: PyQt5
Requires-Dist: pycryptodome
Requires-Dist: pycryptodomex
Requires-Dist: sqlalchemy
